gradescope_auto_py/__init__.py
gradescope_auto_py/__main__.py
gradescope_auto_py/assert_for_pts.py
gradescope_auto_py/folder.py
gradescope_auto_py/grade.py
gradescope_auto_py/grader.py
gradescope_auto_py/grader_config.py
gradescope_auto_py/tmp.py
gradescope_auto_py/util.py
gradescope_auto_py/visibility.py
gradescope_auto_py/gradescope/__init__.py
gradescope_auto_py/gradescope/run_autograder
gradescope_auto_py/gradescope/setup.sh
gradescope_auto_py-0.0.23.dist-info/METADATA
gradescope_auto_py-0.0.23.dist-info/WHEEL
gradescope_auto_py-0.0.23.dist-info/top_level.txt
gradescope_auto_py-0.0.23.dist-info/RECORD
