Metadata-Version: 2.1
Name: gradescope-auto-py
Version: 0.0.23
Summary: a gradescope autograder for python
Author-email: Matt Higger <matt.higger@gmail.com>
Project-URL: Homepage, https://github.com/matthigger/gradescope_auto_py
Classifier: Programming Language :: Python :: 3
Classifier: Operating System :: OS Independent
Requires-Python: >=3.7
Requires-Dist: pipreqs
